byteplug_document-0.1-nspkg.pth
byteplug/document/__init__.py
byteplug/document/document.py
byteplug/document/exception.py
byteplug/document/object.py
byteplug/document/specs.py
byteplug/document/types.py
byteplug/document/utils.py
byteplug_document-0.1.dist-info/LICENSE.txt
byteplug_document-0.1.dist-info/METADATA
byteplug_document-0.1.dist-info/WHEEL
byteplug_document-0.1.dist-info/namespace_packages.txt
byteplug_document-0.1.dist-info/top_level.txt
byteplug_document-0.1.dist-info/RECORD
