Metadata-Version: 2.1
Name: byteplug-document
Version: 0.1
Summary: Byteplug toolkit that implements the Document Validator standard.
Home-page: https://www.byteplug.io/standards/document-validator
Author: Jonathan De Wachter
Author-email: jonathan.dewachter@byteplug.io
License: OSL-3.0
Platform: UNKNOWN
Classifier: License :: OSI Approved :: Open Software License 3.0 (OSL-3.0)
Requires-Python: >=3.9
License-File: LICENSE.txt
Requires-Dist: pyyaml
